pyosmkit/__init__.py
pyosmkit/point.py
pyosmkit/tile.py
pyosmkit/mbtile/__init__.py
pyosmkit/mbtile/filelike.py
pyosmkit/metatile/__init__.py
pyosmkit/metatile/filelike.py
pyosmkit/metatile/metatile.py
pyosmkit/polygon/__init__.py
pyosmkit/polygon/polygon.py
pyosmkit/polygon/raycasting.py
pyosmkit/polygon/region.py
pyosmkit-0.11.data/scripts/osmtool_convert_latlong
pyosmkit-0.11.data/scripts/osmtool_convert_path
pyosmkit-0.11.data/scripts/osmtool_unpack_mbtile
pyosmkit-0.11.data/scripts/osmtool_unpack_metatile
pyosmkit-0.11.dist-info/LICENSE
pyosmkit-0.11.dist-info/METADATA
pyosmkit-0.11.dist-info/WHEEL
pyosmkit-0.11.dist-info/top_level.txt
pyosmkit-0.11.dist-info/RECORD
