Metadata-Version: 2.1
Name: pyosmkit
Version: 0.11
Summary: Library for building OSM tools
Home-page: https://github.com/tierpod/pyosmkit
Author: Pavel Podkorytov
Author-email: pod.pavel@gmail.com
License: MIT
Platform: UNKNOWN
Classifier: Development Status :: 3 - Alpha
Classifier: Programming Language :: Python :: 2
Classifier: Programming Language :: Python :: 3
